ComputeJobRecorder-0.1.1.data/scripts/cjr_query.py
ComputeJobRecorder-0.1.1.data/scripts/cjr_record.py
cjrlib/__init__.py
cjrlib/cjr_db_connection.py
cjrlib/cjr_queries.py
cjrlib/cjr_recorder.py
ComputeJobRecorder-0.1.1.dist-info/LICENSE.txt
ComputeJobRecorder-0.1.1.dist-info/METADATA
ComputeJobRecorder-0.1.1.dist-info/WHEEL
ComputeJobRecorder-0.1.1.dist-info/top_level.txt
ComputeJobRecorder-0.1.1.dist-info/RECORD
