Metadata-Version: 2.1
Name: ComputeJobRecorder
Version: 0.1.1
Summary: A tool for recording a compute job progress.
Home-page: https://www.remotesensing.info/compute_job_recorder
Author: Pete Bunting
Author-email: pfb@aber.ac.uk
License: LICENSE.txt
Platform: UNKNOWN
Classifier: Intended Audience :: Developers
Classifier: Operating System :: OS Independent
Classifier: Programming Language :: Python :: 3.5
Classifier: Programming Language :: Python :: 3.6
Classifier: Programming Language :: Python :: 3.7
Classifier: Programming Language :: Python :: 3.8
